scidirecttrends/__init__.py
scidirecttrends/main.py
scidirecttrends/visualization.py
SciDirectTrends-1.0.1.dist-info/LICENSE
SciDirectTrends-1.0.1.dist-info/METADATA
SciDirectTrends-1.0.1.dist-info/WHEEL
SciDirectTrends-1.0.1.dist-info/entry_points.txt
SciDirectTrends-1.0.1.dist-info/top_level.txt
SciDirectTrends-1.0.1.dist-info/RECORD
