Metadata-Version: 2.1
Name: SciDirectTrends
Version: 1.0.1
Summary: A tool for fetching and visualizing publication trends from ScienceDirect
Home-page: https://github.com/AliRezaBeigy/SciDirectTrends
Author: AliReza Beigy
Author-email: alireza.beigy.rb@gmail.com
License: MIT
Keywords: ScienceDirect,data visualization,publication trends
Platform: nt
Platform: posix
Classifier: Development Status :: 5 - Production/Stable
Classifier: Intended Audience :: Developers
Classifier: License :: OSI Approved :: MIT License
Classifier: Operating System :: OS Independent
Classifier: Programming Language :: Python :: 3
Classifier: Programming Language :: Python :: 3.6
Classifier: Programming Language :: Python :: 3.7
Classifier: Programming Language :: Python :: 3.8
Classifier: Programming Language :: Python :: 3.9
Classifier: Programming Language :: Python :: 3.10
Classifier: Programming Language :: Python :: 3.11
Classifier: Topic :: Scientific/Engineering :: Information Analysis
Classifier: Topic :: Software Development :: Libraries :: Python Modules
Requires-Python: >=3.6
License-File: LICENSE
Requires-Dist: requests
Requires-Dist: matplotlib
Requires-Dist: seaborn
Requires-Dist: numpy
